pycross/__init__.py
pycross/crossword.py
pycross/cwordg.py
pycross/dbapi.py
pycross/forms.py
pycross/gui.py
pycross/guisettings.py
pycross/wordsrc.py
pycross/assets/dic/Sep11-2008.xpf
pycross/assets/dic/de.db
pycross/assets/dic/en.db
pycross/assets/dic/english-words.20
pycross/assets/dic/fr.db
pycross/assets/dic/ru.db
pycross/assets/icons/add-1.png
pycross/assets/icons/add-2.png
pycross/assets/icons/add-3.png
pycross/assets/icons/add.png
pycross/assets/icons/add_col.png
pycross/assets/icons/add_row.png
pycross/assets/icons/addon.png
pycross/assets/icons/ajax-loader.gif
pycross/assets/icons/alarm-clock-1.png
pycross/assets/icons/analytics.png
pycross/assets/icons/api.png
pycross/assets/icons/archive-1.png
pycross/assets/icons/asterisk.png
pycross/assets/icons/asterisk1.png
pycross/assets/icons/back.png
pycross/assets/icons/binoculars.png
pycross/assets/icons/calculator-1.png
pycross/assets/icons/cell-blank.png
pycross/assets/icons/cell-filled.png
pycross/assets/icons/cell-greyed.png
pycross/assets/icons/cells-blank.png
pycross/assets/icons/checked-1.png
pycross/assets/icons/close.png
pycross/assets/icons/cloud-computing-1.png
pycross/assets/icons/cloud-computing-2.png
pycross/assets/icons/cloud-computing-3.png
pycross/assets/icons/cloud-computing-4.png
pycross/assets/icons/cloud-computing-5.png
pycross/assets/icons/cloud-computing.png
pycross/assets/icons/cloud.png
pycross/assets/icons/compose.png
pycross/assets/icons/controls-1.png
pycross/assets/icons/crossword.png
pycross/assets/icons/database-3.png
pycross/assets/icons/delete_col.png
pycross/assets/icons/delete_row.png
pycross/assets/icons/dislike.png
pycross/assets/icons/dust.png
pycross/assets/icons/edit.png
pycross/assets/icons/eject.png
pycross/assets/icons/error.png
pycross/assets/icons/exit.png
pycross/assets/icons/fast-forward-1.png
pycross/assets/icons/fast-forward.png
pycross/assets/icons/file.png
pycross/assets/icons/fitsize.png
pycross/assets/icons/flag-2.png
pycross/assets/icons/flash.png
pycrossword-0.4.0.3.dist-info/LICENSE
pycrossword-0.4.0.3.dist-info/METADATA
pycrossword-0.4.0.3.dist-info/WHEEL
pycrossword-0.4.0.3.dist-info/top_level.txt
pycrossword-0.4.0.3.dist-info/RECORD
