Metadata-Version: 2.1
Name: pycrossword
Version: 0.4.0.3
Summary: pycrossword - the Python Crossword Puzzle Generator and Editor
Home-page: https://github.com/S0mbre/crossword.git
Author: Iskander Shafikov (S0mbre)
Author-email: s00mbre@gmail.com
License: UNKNOWN
Platform: UNKNOWN
Classifier: Programming Language :: Python :: 3
Classifier: License :: OSI Approved :: GNU General Public License v3 (GPLv3)
Classifier: Operating System :: OS Independent
Requires-Python: >=3.7
